contact_email_address_local/__init__.py
contact_email_address_local/contact_email_addresses_constants.py
contact_email_address_local/contact_email_addresses_local.py
contact_email_address_local-0.0.40.1234.dist-info/METADATA
contact_email_address_local-0.0.40.1234.dist-info/WHEEL
contact_email_address_local-0.0.40.1234.dist-info/top_level.txt
contact_email_address_local-0.0.40.1234.dist-info/RECORD
